match_extensions/__init__.py
match_extensions/basic.py
jmatch-0.4.dist-info/LICENCE
jmatch-0.4.dist-info/METADATA
jmatch-0.4.dist-info/WHEEL
jmatch-0.4.dist-info/entry_points.txt
jmatch-0.4.dist-info/top_level.txt
jmatch-0.4.dist-info/RECORD
