Metadata-Version: 2.1
Name: jmatch
Version: 0.4
Summary: Simple test-suite for json/yaml files, optimized for CI pipelines.
Home-page: https://gitlab.rlp.net/jdillenberger/jmatch
Author: Jan Dillenberger
Author-email: jdillenberger@uni-koblenz.de
License: UNKNOWN
Project-URL: Bug Reports, https://gitlab.rlp.net/jdillenberger/jmatch/issues/new
Project-URL: Source, https://gitlab.rlp.net/jdillenberger/jmatch
Platform: UNKNOWN
Classifier: Programming Language :: Python :: 3
Classifier: License :: OSI Approved :: MIT License
Classifier: Operating System :: OS Independent
Requires-Python: >=3.*
Requires-Dist: requests
Requires-Dist: termcolor
Requires-Dist: pyyaml
